setup.cfg
setup.py
zeonapi/__init__.py
zeonapi/dbdrivers.py
zeonapi/formatters.py
zeonapi/mailparserimap.py
zeonapi.egg-info/PKG-INFO
zeonapi.egg-info/SOURCES.txt
zeonapi.egg-info/dependency_links.txt
zeonapi.egg-info/requires.txt
zeonapi.egg-info/top_level.txt