Metadata-Version: 1.1
Name: zeonapi
Version: 0.0.1
Summary: ZEON PBX API library
Home-page: https://github.com/soshnikov/zeonapi
Author: Ivan Soshnikov
Author-email: ivan@wtp.su
License: UNKNOWN
Download-URL: https://github.com/soshnikov/zeonapi/archive/master.zip
Platform: UNKNOWN
